mcp_server_bailian_video_synthesis/__init__.py
mcp_server_bailian_video_synthesis/server.py
mcp_server_bailian_video_synthesis-1.0.3.dist-info/METADATA
mcp_server_bailian_video_synthesis-1.0.3.dist-info/WHEEL
mcp_server_bailian_video_synthesis-1.0.3.dist-info/entry_points.txt
mcp_server_bailian_video_synthesis-1.0.3.dist-info/top_level.txt
mcp_server_bailian_video_synthesis-1.0.3.dist-info/RECORD
