Metadata-Version: 2.4
Name: mcp-server-bailian-video-synthesis
Version: 1.0.3
Summary: 阿里云百炼-通义万相视频编辑统一模型MCP服务器
Author-email: John Chen <john.chen@example.com>
License-Expression: MIT
Project-URL: Homepage, https://github.com/johnchen/mcp-server-bailian-video-synthesis
Project-URL: Repository, https://github.com/johnchen/mcp-server-bailian-video-synthesis
Project-URL: Documentation, https://github.com/johnchen/mcp-server-bailian-video-synthesis#readme
Project-URL: Bug Tracker, https://github.com/johnchen/mcp-server-bailian-video-synthesis/issues
Keywords: mcp,model-context-protocol,aliyun,bailian,video,ai
Classifier: Development Status :: 4 - Beta
Classifier: Intended Audience :: Developers
Classifier: Operating System :: OS Independent
Classifier: Programming Language :: Python :: 3
Classifier: Programming Language :: Python :: 3.8
Classifier: Programming Language :: Python :: 3.9
Classifier: Programming Language :: Python :: 3.10
Classifier: Programming Language :: Python :: 3.11
Classifier: Programming Language :: Python :: 3.12
Classifier: Topic :: Software Development :: Libraries :: Python Modules
Classifier: Topic :: Internet :: WWW/HTTP :: HTTP Servers
Classifier: Topic :: Multimedia :: Video
Requires-Python: >=3.8
Requires-Dist: mcp>=1.0.0
Requires-Dist: httpx>=0.24.0
Requires-Dist: asyncio
Provides-Extra: dev
Requires-Dist: pytest>=7.0.0; extra == "dev"
Requires-Dist: pytest-asyncio>=0.21.0; extra == "dev"
Requires-Dist: black>=22.0.0; extra == "dev"
Requires-Dist: isort>=5.0.0; extra == "dev"
Requires-Dist: mypy>=1.0.0; extra == "dev"
